PyLOD/PyLOD.py
PyLOD/__init__.py
PyLOD-0.1.12.dist-info/METADATA
PyLOD-0.1.12.dist-info/RECORD
PyLOD-0.1.12.dist-info/WHEEL
PyLOD-0.1.12.dist-info/top_level.txt
