Metadata-Version: 2.1
Name: PyLOD
Version: 0.1.12
Summary: PyLOD is a Python wrapper for exposing Linked Open Data from public SPARQL-served endpoints.
Home-page: https://github.com/panmitz/PyLOD
Author: Panos Mitzias
Author-email: pmitzias@gmail.com
License: UNKNOWN
Platform: UNKNOWN
Classifier: Programming Language :: Python
Classifier: Programming Language :: Python :: 2
Classifier: Programming Language :: Python :: 3
Classifier: Operating System :: OS Independent
Requires-Dist: sparqlwrapper
